fitter/__init__.py
fitter/base_fitter.py
fitter/constraint_reader.py
fitter/data_fitter.py
fitter/data_model.py
fitter/data_preprocessor.py
fitter/inclusive_decays_weights.py
fitter/inclusive_sample_weights.py
fitter/pchain.py
fitter/pdg_utils.py
fitter/prec.py
fitter/prec_scales.py
fitter/sim_fitter.py
fitter_data/__init__.py
fitter_data/rare/electron/bdkstee.yaml
fitter_data/rare/electron/bsphiee.yaml
fitter_data/rare/electron/bukstee.yaml
fitter_data/rare/electron/ccbar.yaml
fitter_data/rare/electron/combinatorial.yaml
fitter_data/rare/electron/data.yaml
fitter_data/rare/electron/jpsi_leakage.yaml
fitter_data/rare/electron/psi2_leakage.yaml
fitter_data/rare/electron/signal_non_parametric.yaml
fitter_data/rare/electron/signal_parametric.yaml
fitter_data/rare/muon/data.yaml
fitter_data/rare/muon/exp.yaml
fitter_data/rare/muon/signal.yaml
fitter_data/reso/electron/ccbar.yaml
fitter_data/reso/electron/combinatorial.yaml
fitter_data/reso/electron/data.yaml
fitter_data/reso/electron/signal.yaml
fitter_data/reso/muon/data.yaml
fitter_data/reso/muon/exp.yaml
fitter_data/reso/muon/signal.yaml
fitter_data/tests/bdkstee.yaml
fitter_data/tests/bsphiee.yaml
fitter_data/tests/bukstee.yaml
fitter_data/tests/ccbar.yaml
fitter_data/tests/combinatorial.yaml
fitter_data/tests/data_toy.yaml
fitter_data/tests/signal_electron.yaml
fitter_data/tests/signal_muon.yaml
fitter_data/tests/signal_toy.yaml
rx_fitter-1.1.dev351.dist-info/METADATA
rx_fitter-1.1.dev351.dist-info/WHEEL
rx_fitter-1.1.dev351.dist-info/entry_points.txt
rx_fitter-1.1.dev351.dist-info/RECORD
