Metadata-Version: 2.3
Name: rx_fitter
Version: 1.1.dev351
Summary: Framework used to handle fits to data and simulation
Requires-Python: >=3.10, <3.13
Classifier: Programming Language :: Python :: 3
Classifier: Programming Language :: Python :: 3.10
Classifier: Programming Language :: Python :: 3.11
Classifier: Programming Language :: Python :: 3.12
Provides-Extra: dev
Requires-Dist: matplotlib
Requires-Dist: mplhep
Requires-Dist: numpy
Requires-Dist: omegaconf
Requires-Dist: pytest ; extra == "dev"
Requires-Dist: python-slugify
